Metadata-Version: 2.1
Name: hpformula
Version: 1.20211025
Summary: hpformula for lyy
Author: lyy
Author-email: 
License: MIT
License-File: LICENSE
